clean_alchemy/__init__.py
clean_alchemy/base.py
clean_alchemy/base_dao.py
clean_alchemy/base_entity.py
clean_alchemy/base_repo.py
clean_alchemy/base_service.py
clean_alchemy/config.py
clean_alchemy-0.1.14.dist-info/LICENSE
clean_alchemy-0.1.14.dist-info/METADATA
clean_alchemy-0.1.14.dist-info/WHEEL
clean_alchemy-0.1.14.dist-info/top_level.txt
clean_alchemy-0.1.14.dist-info/RECORD
